[
    {
        "photo_id" : 1,
        "photo_url": "https://i.ibb.co/jbG8dWY/output-onlinepngtools-6.png"
    },
    {
        "photo_id" : 2,
        "photo_url": "https://i.ibb.co/J5P8W0Z/output-onlinepngtools-5.png"
    },
    {
        "photo_id" : 3,
        "photo_url": "https://i.ibb.co/Hp4wJhy/output-onlinepngtools-4.png"
    },
    {
        "photo_id" : 4,
        "photo_url": "https://i.ibb.co/Cvk6PDy/output-onlinepngtools-3.png"
    },
    {
        "photo_id" : 5,
        "photo_url": "https://i.ibb.co/yqYgKqT/output-onlinepngtools-2.png"
    },
    {
        "photo_id": 6,
        "photo_url": "https://i.ibb.co/J7FSVPS/output-onlinepngtools-1.png"
    },
    {
        "photo_id": 7,
        "photo_url": "https://i.ibb.co/Sv8ZGtn/output-onlinepngtools.png"
    },
    {
        "photo_id": 8,
        "photo_url": "https://i.ibb.co/23qH24H/output-onlinepngtools.png"
    },
    {
        "photo_id": 9,
        "photo_url": "https://i.ibb.co/5FS1Q4X/output-onlinepngtools-5.png"
    },
    {
        "photo_id": 10,
        "photo_url": "https://i.ibb.co/PMJLXFh/output-onlinepngtools-4.png"
    },
    {
        "photo_id": 11,
        "photo_url": "https://i.ibb.co/HKR00zH/output-onlinepngtools-3.png"
    },
    {
        "photo_id": 12,
        "photo_url": "https://i.ibb.co/DG4kzFr/output-onlinepngtools-2.png"
    },
    {
        "photo_id": 13,
        "photo_url": "https://i.ibb.co/yq9DcKX/output-onlinepngtools-1.png"
    }
]